openram/LICENSE
openram/MANIFEST.in
openram/Makefile
openram/README.md
openram/VERSION
openram/__init__.py
openram/common.py
openram/install_conda.sh
openram/openram.mk
openram/pyproject.toml
openram/requirements.txt
openram/rom_compiler.py
openram/setpaths.sh
openram/setup.cfg
openram/setup.py
openram/sram_char.py
openram/sram_compiler.py
openram/sram_func.py
openram/compiler/Makefile
openram/compiler/debug.py
openram/compiler/globals.py
openram/compiler/options.py
openram/compiler/rom.py
openram/compiler/rom_config.py
openram/compiler/sram.py
openram/compiler/sram_config.py
openram/compiler/sram_factory.py
openram/compiler/base/__init__.py
openram/compiler/base/channel_route.py
openram/compiler/base/contact.py
openram/compiler/base/delay_data.py
openram/compiler/base/design.py
openram/compiler/base/errors.py
openram/compiler/base/geometry.py
openram/compiler/base/hierarchy_design.py
openram/compiler/base/hierarchy_layout.py
openram/compiler/base/hierarchy_spice.py
openram/compiler/base/lef.py
openram/compiler/base/logical_effort.py
openram/compiler/base/pin_layout.py
openram/compiler/base/power_data.py
openram/compiler/base/rom_verilog.py
openram/compiler/base/route.py
openram/compiler/base/timing_graph.py
openram/compiler/base/utils.py
openram/compiler/base/vector.py
openram/compiler/base/vector3d.py
openram/compiler/base/verilog.py
openram/compiler/base/wire.py
openram/compiler/base/wire_path.py
openram/compiler/base/wire_spice_model.py
openram/compiler/characterizer/__init__.py
openram/compiler/characterizer/analytical_util.py
openram/compiler/characterizer/cacti.py
openram/compiler/characterizer/charutils.py
openram/compiler/characterizer/delay.py
openram/compiler/characterizer/elmore.py
openram/compiler/characterizer/fake_sram.py
openram/compiler/characterizer/functional.py
openram/compiler/characterizer/lib.py
openram/compiler/characterizer/linear_regression.py
openram/compiler/characterizer/measurements.py
openram/compiler/characterizer/model_check.py
openram/openram.egg-info/PKG-INFO
openram/openram.egg-info/SOURCES.txt
openram/openram.egg-info/dependency_links.txt
openram/openram.egg-info/requires.txt
openram/openram.egg-info/top_level.txt
openram-1.2.48.dist-info/LICENSE
openram-1.2.48.dist-info/METADATA
openram-1.2.48.dist-info/WHEEL
openram-1.2.48.dist-info/top_level.txt
openram-1.2.48.dist-info/RECORD
