Metadata-Version: 2.1
Name: openram
Version: 1.2.48
Summary: An open-source static random access memory (SRAM) compiler
Home-page: https://openram.org/
Download-URL: https://github.com/VLSIDA/OpenRAM/releases
Author: Matthew Guthaus
Author-email: mrg+vlsida@ucsc.edu
License: BSD 3-Clause
Project-URL: Bug Tracker, https://github.com/VLSIDA/OpenRAM/issues
Project-URL: Documentation, https://github.com/VLSIDA/OpenRAM/blob/stable/docs/source/index.md
Project-URL: Source Code, https://github.com/VLSIDA/OpenRAM
Keywords: sram,magic,gds,netgen,ngspice,netlist
Classifier: Development Status :: 5 - Production/Stable
Classifier: Intended Audience :: Developers
Classifier: Intended Audience :: Science/Research
Classifier: License :: OSI Approved :: BSD License
Classifier: Natural Language :: English
Classifier: Operating System :: Unix
Classifier: Programming Language :: Python
Classifier: Programming Language :: Python :: 3
Classifier: Programming Language :: Python :: 3 :: Only
Classifier: Topic :: Scientific/Engineering
Classifier: Topic :: Software Development
Classifier: Topic :: System :: Hardware
Requires-Python: >=3.5
License-File: LICENSE
Requires-Dist: scikit-learn >=0.22.2
Requires-Dist: coverage >=4.5.2
Requires-Dist: scipy >=1.3.3
Requires-Dist: numpy >=1.17.4
Requires-Dist: python-subunit >=1.4.0
Requires-Dist: unittest2 >=1.1.0
Requires-Dist: volare >=0.15.2
